aiomysql_type/__init__.py
aiomysql_type/py.typed
aiomysql_type-0.1.2.dist-info/licenses/LICENSE
aiomysql_type-0.1.2.dist-info/METADATA
aiomysql_type-0.1.2.dist-info/WHEEL
aiomysql_type-0.1.2.dist-info/top_level.txt
aiomysql_type-0.1.2.dist-info/RECORD
