Metadata-Version: 2.4
Name: aiomysql-type
Version: 0.1.2
Summary: Functions and types to facilitate mysql typed queries
License-Expression: Apache-2.0
Requires-Python: >=3.12
License-File: LICENSE
Requires-Dist: aiomysql
Dynamic: license-file
